{"title":"Perguntas Frequentes (FAQ)","markdown":{"yaml":"---\ntitle: \"Perguntas Frequentes (FAQ)\"\nparams: \n  link_inscricao: \"https://www.ime.usp.br/~verao/\"\n---","containsRefs":false,"markdown":"\n\n1. O curso será online ou presencial?\n\n> O curso será oferecido de forma online.\n\n2. Apenas alunos da USP podem participar do curso?\n\n> As inscrições serão abertas para todas as pessoas interessadas.\n\n3. Como posso me inscrever?\n\n> A inscrição será realizada através do IME-USP. Acompanhe as informações na página do Programa de Verão do IME-USP:  <`r params$link_inscricao`>\n\n4. O curso é gratuito?\n\n> Não, o curso é pago. Acompanhe as informações na página do Programa de Verão do IME-USP: <`r params$link_inscricao`>\n\n"},"formats":{"html":{"execute":{"fig.width":7,"fig.height":5,"fig.format":"retina","fig.dpi":96,"error":false,"eval":true,"cache":null,"freeze":false,"echo":true,"output":true,"warning":true,"include":true,"keep-md":false,"keep-ipynb":false,"ipynb":null,"enabled":null,"daemon":null,"daemon-restart":false,"debug":false,"engine":"knitr"},"render":{"keep-tex":false,"keep-yaml":false,"keep-source":false,"keep-hidden":false,"prefer-html":false,"output-divs":true,"output-ext":"html","fig-align":"default","code-fold":"none","code-overflow":"scroll","code-link":false,"code-line-numbers":false,"code-tools":false,"merge-includes":true,"self-contained-math":false,"latex-auto-mk":true,"latex-auto-install":true,"latex-clean":true,"latex-max-runs":10,"latex-makeindex":"makeindex","latex-makeindex-opts":[],"latex-tlmgr-opts":[],"latex-output-dir":null,"link-external-icon":false,"link-external-newwindow":false},"pandoc":{"standalone":true,"to":"html","css":["styles.css"],"toc":true,"output-file":"faq.html"},"language":{},"metadata":{"lang":"pt","theme":{"light":"yeti","dark":"superhero"},"toc-title":"Nessa página","title":"Perguntas Frequentes (FAQ)","params":{"link_inscricao":"https://www.ime.usp.br/~verao/"}},"extensions":{"book":{"multiFile":true}}}}}